setup.py
digBusinessTypeExtractor/__init__.py
digBusinessTypeExtractor/business_type_extractor.py
digBusinessTypeExtractor/documentation_classification.py
digBusinessTypeExtractor.egg-info/PKG-INFO
digBusinessTypeExtractor.egg-info/SOURCES.txt
digBusinessTypeExtractor.egg-info/dependency_links.txt
digBusinessTypeExtractor.egg-info/requires.txt
digBusinessTypeExtractor.egg-info/top_level.txt
digBusinessTypeExtractor/data/dataset.csv
test/__init__.py
test/test_business_type_extractor.py
test/test_wedc.py