Metadata-Version: 1.1
Name: digBusinessTypeExtractor
Version: 0.3.0
Summary: digBusinessTypeExtractor
Home-page: https://github.com/usc-isi-i2/dig-business-type-extractor
Author: Lingzhe Teng
Author-email: zwein27@gmail.com
License: UNKNOWN
Download-URL: https://github.com/usc-isi-i2/dig-business-type-extractor
Keywords: business,type,extractor
Platform: UNKNOWN
